README.md
setup.py
netease_audiodiff/AudioComparator.py
netease_audiodiff/AudioSearchComparator.py
netease_audiodiff/AudioSearcher.py
netease_audiodiff/__init__.py
netease_audiodiff/afp_config.py
netease_audiodiff/audio_diff.py
netease_audiodiff/audio_processor.py
netease_audiodiff/audio_utils.py
netease_audiodiff/bat_test.py
netease_audiodiff/config.json
netease_audiodiff/ffmpeg.exe
netease_audiodiff/ffprobe.exe
netease_audiodiff/fp_processor.py
netease_audiodiff.egg-info/PKG-INFO
netease_audiodiff.egg-info/SOURCES.txt
netease_audiodiff.egg-info/dependency_links.txt
netease_audiodiff.egg-info/requires.txt
netease_audiodiff.egg-info/top_level.txt