Metadata-Version: 2.1
Name: netease-audiodiff
Version: 1.0.8
Summary: With this Toolset and one audio cable you can simply built end2end audio test paltform base on mac,which means,Its very Lightweight，Easy to build and carry
Home-page: https://g.hz.netease.com/hzpansongsheng/audio_diff/-/tree/feature/pypi
Author:  PAN SONGSHENG
Author-email: hzpansongsheng@corp.netease.com
License: MIT
Platform: UNKNOWN
Classifier: Programming Language :: Python :: 3
Classifier: License :: OSI Approved :: MIT License
Classifier: Operating System :: OS Independent
Classifier: Operating System :: MacOS :: MacOS X
Classifier: Operating System :: Microsoft :: Windows
Requires-Python: >=3.7
